LICENSE
p123/__init__.py
p123/py.typed
p123/tool/__init__.py
python_123_client-0.0.5.2.dist-info/LICENSE
python_123_client-0.0.5.2.dist-info/METADATA
python_123_client-0.0.5.2.dist-info/WHEEL
python_123_client-0.0.5.2.dist-info/RECORD
