Metadata-Version: 2.1
Name: python-123-client
Version: 0.0.5.2
Summary: Python wrapper for 123 webdisk.
Home-page: https://github.com/ChenyangGao/web-mount-packs/tree/main/python-123-client
License: MIT
Keywords: 123,webdisk,client
Author: ChenyangGao
Author-email: wosiwujm@gmail.com
Requires-Python: >=3.12,<4.0
Classifier: Development Status :: 4 - Beta
Classifier: Intended Audience :: Developers
Classifier: License :: OSI Approved :: MIT License
Classifier: Operating System :: OS Independent
Classifier: Programming Language :: Python
Classifier: Programming Language :: Python :: 3
Classifier: Programming Language :: Python :: 3.12
Classifier: Programming Language :: Python :: 3.13
Classifier: Programming Language :: Python :: 3 :: Only
Classifier: Topic :: Software Development
Classifier: Topic :: Software Development :: Libraries
Classifier: Topic :: Software Development :: Libraries :: Python Modules
Requires-Dist: aiofile
Requires-Dist: httpx
Requires-Dist: httpx_request (>=0.1.2)
Requires-Dist: multidict
Requires-Dist: orjson
Requires-Dist: python-asynctools (>=0.0.8.2)
Requires-Dist: python-encode_uri (>=0.0.3)
Requires-Dist: python-filewrap (>=0.2.6.1)
Requires-Dist: python-hashtools (>=0.0.3.3)
Requires-Dist: python-http_request (>=0.0.7)
Requires-Dist: python-httpfile (>=0.0.5)
Requires-Dist: python-iterutils (>=0.2)
Requires-Dist: python-property (>=0.0.3)
Requires-Dist: yarl
Project-URL: Repository, https://github.com/ChenyangGao/web-mount-packs/tree/main/python-123-client
